INSTALL.rst
INSTALL.xml
MANIFEST.in
Makefile
NEWS.rst
NEWS.xml
OLDMIGRATION.rst
OLDMIGRATION.xml
OLDNEWS.rst
OLDNEWS.xml
README.rst
setup.cfg
setup.py
scripts/ucp.py
src/ll/__init__.py
src/ll/_ansistyle.c
src/ll/_misc.c
src/ll/_url.c
src/ll/_xml_codec.c
src/ll/_xml_codec_include.c
src/ll/ansistyle.py
src/ll/astyle.py
src/ll/color.py
src/ll/daemon.py
src/ll/make.py
src/ll/misc.py
src/ll/sisyphus.py
src/ll/url.py
src/ll/xml_codec.py
src/ll/xpit.py
src/ll/scripts/__init__.py
src/ll/scripts/ucp.py
src/ll_core.egg-info/PKG-INFO
src/ll_core.egg-info/SOURCES.txt
src/ll_core.egg-info/dependency_links.txt
src/ll_core.egg-info/entry_points.txt
src/ll_core.egg-info/namespace_packages.txt
src/ll_core.egg-info/not-zip-safe
src/ll_core.egg-info/top_level.txt
test/test_ansistyle.py
test/test_misc_decorators.py
test/test_misc_iter.py
test/test_misc_pool.py
test/test_url.py
test/test_url_open.py
test/test_url_windows.py
test/test_xml_codec.py
test/test_xpit.py
