Metadata-Version: 1.0
Name: ll-core
Version: 1.11.1
Summary: LivingLogic base package: ansistyle, color, make, sisyphus, xpit, url, xml_codec
Home-page: http://www.livinglogic.de/Python/core/
Author: Walter Doerwald
Author-email: walter@livinglogic.de
License: MIT
Download-URL: http://www.livinglogic.de/Python/core/Download.html
Keywords: property,decorator,iterator,ANSI,escape sequence,color,terminal,RGB,HSV,HSB,HLS,CSS,red,green,blue,hue,saturation,value,brightness,luminance,make,build,cron,job,daemon,UNIX,fork,URL,RFC 2396,HTTP,FTP,ssh,py.execnet,text,template,processing instruction,XML,codec,decoding
Platform: UNKNOWN
Classifier: Development Status :: 5 - Production/Stable
Classifier: Intended Audience :: Developers
Classifier: License :: OSI Approved :: MIT License
Classifier: Operating System :: OS Independent
Classifier: Programming Language :: Python
Classifier: Topic :: Software Development :: Libraries :: Python Modules
Classifier: Topic :: Terminals
Classifier: Topic :: Text Processing :: General
Classifier: Topic :: Multimedia :: Graphics
Classifier: Topic :: Software Development :: Build Tools
Classifier: Environment :: No Input/Output (Daemon)
Classifier: Operating System :: POSIX
Classifier: Topic :: Internet
Classifier: Topic :: Internet :: File Transfer Protocol (FTP)
Classifier: Topic :: Internet :: WWW/HTTP
Classifier: Topic :: Text Processing :: Filters
Classifier: Topic :: Text Processing :: Markup :: XML
